main.py
KASABLADEV-0.1.dist-info/METADATA
KASABLADEV-0.1.dist-info/WHEEL
KASABLADEV-0.1.dist-info/top_level.txt
KASABLADEV-0.1.dist-info/RECORD
