Metadata-Version: 2.1
Name: KASABLADEV
Version: 0.1
Summary: KASA
Home-page: UNKNOWN
Author: Christelle.Yemeck
Author-email: UNKNOWN
License: BSD
Platform: UNKNOWN
